cyyjson.abi3.so
yyjson/__init__.py
yyjson/__init__.pyi
yyjson/binding.c
yyjson/decimal.h
yyjson/document.c
yyjson/document.h
yyjson/memory.c
yyjson/memory.h
yyjson/yyjson.c
yyjson/yyjson.h
vtx_yyjson-4.3.0.dist-info/METADATA
vtx_yyjson-4.3.0.dist-info/WHEEL
vtx_yyjson-4.3.0.dist-info/top_level.txt
vtx_yyjson-4.3.0.dist-info/RECORD
vtx_yyjson-4.3.0.dist-info/licenses/LICENSE
