Metadata-Version: 2.4
Name: vtx-yyjson
Version: 4.3.0
Summary: JSON parser & serializer built on yyjson
Author-email: The Vertex Project LLC <root@vertex.link>, Tyler Kennedy <tk@tkte.ch>
License-Expression: MIT
Project-URL: Homepage, https://vertex.link
Project-URL: Repository, https://github.com/vertexproject/vertex_py_yyjson/tree/vtx_main
Keywords: json,parser,serializer,patcher
Classifier: Development Status :: 5 - Production/Stable
Classifier: Intended Audience :: Developers
Classifier: Programming Language :: Python :: 3.11
Classifier: Programming Language :: Python :: 3.12
Classifier: Programming Language :: Python :: 3.13
Classifier: Programming Language :: Python :: Implementation :: CPython
Classifier: Operating System :: OS Independent
Classifier: Topic :: Software Development :: Libraries :: Python Modules
License-File: LICENSE
Provides-Extra: test
Requires-Dist: pytest; extra == "test"
Provides-Extra: release
Requires-Dist: sphinx; extra == "release"
Requires-Dist: sphinx-copybutton; extra == "release"
Requires-Dist: ghp-import; extra == "release"
Requires-Dist: bumpversion; extra == "release"
Requires-Dist: black; extra == "release"
Requires-Dist: furo; extra == "release"
Dynamic: license-file
